{
  "image_index": 0,
  "image_filename": "CLEVR_new_000000.png",
  "objects": [
    {
      "pixel_coords": [
        180,
        106,
        11.943315505981445
      ],
      "color": "yellow",
      "shape": "sphere",
      "material": "metal",
      "size": "small",
      "3d_coords": [
        0.1783720701932907,
        0.7540301084518433,
        0.3499999940395355
      ],
      "rotation": 242.6215904861604
    },
    {
      "pixel_coords": [
        201,
        89,
        13.15228271484375
      ],
      "color": "gray",
      "shape": "cylinder",
      "material": "rubber",
      "size": "small",
      "3d_coords": [
        -0.35769981145858765,
        2.281416893005371,
        0.3499999940395355
      ],
      "rotation": 276.39437184373753
    },
    {
      "pixel_coords": [
        223,
        115,
        11.41500473022461
      ],
      "color": "brown",
      "shape": "cube",
      "material": "metal",
      "size": "small",
      "3d_coords": [
        1.5105977058410645,
        1.4147624969482422,
        0.3499999940395355
      ],
      "rotation": 190.26864436218284
    },
    {
      "pixel_coords": [
        149,
        145,
        9.194456100463867
      ],
      "color": "yellow",
      "shape": "sphere",
      "material": "metal",
      "size": "large",
      "3d_coords": [
        1.8301969766616821,
        -1.8868159055709839,
        0.699999988079071
      ],
      "rotation": 311.04267093364695
    },
    {
      "pixel_coords": [
        251,
        91,
        12.216690063476562
      ],
      "color": "purple",
      "shape": "cube",
      "material": "metal",
      "size": "large",
      "3d_coords": [
        1.3658498525619507,
        2.9907994270324707,
        0.699999988079071
      ],
      "rotation": 169.76771752531567
    },
    {
      "pixel_coords": [
        88,
        131,
        10.517651557922363
      ],
      "color": "green",
      "shape": "cylinder",
      "material": "metal",
      "size": "small",
      "3d_coords": [
        -0.3781699240207672,
        -2.485077381134033,
        0.3499999940395355
      ],
      "rotation": 287.3449942271271
    },
    {
      "pixel_coords": [
        144,
        81,
        13.835407257080078
      ],
      "color": "purple",
      "shape": "sphere",
      "material": "rubber",
      "size": "small",
      "3d_coords": [
        -2.3470849990844727,
        1.1043587923049927,
        0.3499999940395355
      ],
      "rotation": 253.36312474961008
    }
  ],
  "split": "new",
  "directions": {
    "left": [
      -0.6563112735748291,
      -0.7544902563095093,
      0.0
    ],
    "right": [
      0.6563112735748291,
      0.7544902563095093,
      -0.0
    ],
    "front": [
      0.754490315914154,
      -0.6563112735748291,
      -0.0
    ],
    "below": [
      -0.0,
      -0.0,
      -1.0
    ],
    "above": [
      0.0,
      0.0,
      1.0
    ],
    "behind": [
      -0.754490315914154,
      0.6563112735748291,
      0.0
    ]
  },
  "relationships": {
    "left": [
      [
        3,
        5,
        6
      ],
      [
        0,
        3,
        5,
        6
      ],
      [
        0,
        1,
        3,
        5,
        6
      ],
      [
        5,
        6
      ],
      [
        0,
        1,
        2,
        3,
        5,
        6
      ],
      [],
      [
        5
      ]
    ],
    "right": [
      [
        1,
        2,
        4
      ],
      [
        2,
        4
      ],
      [
        4
      ],
      [
        0,
        1,
        2,
        4
      ],
      [],
      [
        0,
        1,
        2,
        3,
        4,
        6
      ],
      [
        0,
        1,
        2,
        3,
        4
      ]
    ],
    "front": [
      [
        2,
        3,
        5
      ],
      [
        0,
        2,
        3,
        4,
        5
      ],
      [
        3,
        5
      ],
      [],
      [
        0,
        2,
        3,
        5
      ],
      [
        3
      ],
      [
        0,
        1,
        2,
        3,
        4,
        5
      ]
    ],
    "behind": [
      [
        1,
        4,
        6
      ],
      [
        6
      ],
      [
        0,
        1,
        4,
        6
      ],
      [
        0,
        1,
        2,
        4,
        5,
        6
      ],
      [
        1,
        6
      ],
      [
        0,
        1,
        2,
        4,
        6
      ],
      []
    ]
  }
}